{"package": {"All_Weights": {"Bias_Weight": 83.67976573381944, "Categorical_Variables": {}, "Numerical_Variables": {"bpf_block_irq": {"scale": 21.666666666666668, "mean": 0, "variance": 0, "weight": 0.560310617004458}, "bpf_cpu_time_us": {"scale": 91498.0, "mean": 0, "variance": 0, "weight": 723.8751701723295}, "bpf_net_rx_irq": {"scale": 12680.666666666668, "mean": 0, "variance": 0, "weight": 0.0}, "bpf_net_tx_irq": {"scale": 1.6666666666666667, "mean": 0, "variance": 0, "weight": 0.0}}}}, "core": {"All_Weights": {"Bias_Weight": 0.0, "Categorical_Variables": {}, "Numerical_Variables": {"bpf_block_irq": {"scale": 21.666666666666668, "mean": 0, "variance": 0, "weight": 0.0}, "bpf_cpu_time_us": {"scale": 91498.0, "mean": 0, "variance": 0, "weight": 0.0}, "bpf_net_rx_irq": {"scale": 12680.666666666668, "mean": 0, "variance": 0, "weight": 0.0}, "bpf_net_tx_irq": {"scale": 1.6666666666666667, "mean": 0, "variance": 0, "weight": 0.0}}}}, "uncore": {"All_Weights": {"Bias_Weight": 0.0, "Categorical_Variables": {}, "Numerical_Variables": {"bpf_block_irq": {"scale": 21.666666666666668, "mean": 0, "variance": 0, "weight": 0.0}, "bpf_cpu_time_us": {"scale": 91498.0, "mean": 0, "variance": 0, "weight": 0.0}, "bpf_net_rx_irq": {"scale": 12680.666666666668, "mean": 0, "variance": 0, "weight": 0.0}, "bpf_net_tx_irq": {"scale": 1.6666666666666667, "mean": 0, "variance": 0, "weight": 0.0}}}}, "dram": {"All_Weights": {"Bias_Weight": 5.098160268207847, "Categorical_Variables": {}, "Numerical_Variables": {"bpf_block_irq": {"scale": 21.666666666666668, "mean": 0, "variance": 0, "weight": 19.81495315514411}, "bpf_cpu_time_us": {"scale": 91498.0, "mean": 0, "variance": 0, "weight": 46.94423284984572}, "bpf_net_rx_irq": {"scale": 12680.666666666668, "mean": 0, "variance": 0, "weight": 0.0}, "bpf_net_tx_irq": {"scale": 1.6666666666666667, "mean": 0, "variance": 0, "weight": 0.0}}}}}